archivos/__init__.py
archivos/class_hist.py
HISTOGRAMS_IC-1.0.dist-info/METADATA
HISTOGRAMS_IC-1.0.dist-info/WHEEL
HISTOGRAMS_IC-1.0.dist-info/top_level.txt
HISTOGRAMS_IC-1.0.dist-info/RECORD
