Metadata-Version: 2.1
Name: HISTOGRAMS-IC
Version: 1.0
Summary: Esta libreria genera histogramas de las variables numericas a partir de un csv
Author: Irene y Cecilia
Author-email: cecilia.bilbao@alumni.mondragon.edu
Requires-Dist: pandas
